{"elapsed":"0.389","endpoint-url":"https://cbccrmdata.blob.core.windows.net/noteattachment/CBC-Fees-and-charges-Government-agreement-transactions-Government%20Agreement%20transactions_20201202.csv","entry-date":"2021-02-24T00:11:15.836119","request-headers":{"Accept":"*/*","Accept-Encoding":"gzip, deflate","Connection":"keep-alive","User-Agent":"Digital Land"},"response-headers":{"Content-Length":"215","Content-Type":"application/xml","Date":"Wed, 24 Feb 2021 00:11:28 GMT","Server":"Windows-Azure-Blob/1.0 Microsoft-HTTPAPI/2.0","x-ms-request-id":"4e46e8e9-201e-011f-3a41-0ab319000000","x-ms-version":"2009-09-19"},"ssl-verify":true,"status":"404"}